README.txt
setup.py
src/bdbdatastore.egg-info/PKG-INFO
src/bdbdatastore.egg-info/SOURCES.txt
src/bdbdatastore.egg-info/dependency_links.txt
src/bdbdatastore.egg-info/not-zip-safe
src/bdbdatastore.egg-info/requires.txt
src/bdbdatastore.egg-info/top_level.txt
src/google/__init__.py
src/google/protobuf/__init__.py
src/google/protobuf/descriptor.py
src/google/protobuf/descriptor_pb2.py
src/google/protobuf/message.py
src/google/protobuf/reflection.py
src/google/protobuf/service.py
src/google/protobuf/service_reflection.py
src/google/protobuf/text_format.py
src/google/protobuf/internal/__init__.py
src/google/protobuf/internal/containers.py
src/google/protobuf/internal/decoder.py
src/google/protobuf/internal/encoder.py
src/google/protobuf/internal/input_stream.py
src/google/protobuf/internal/message_listener.py
src/google/protobuf/internal/output_stream.py
src/google/protobuf/internal/type_checkers.py
src/google/protobuf/internal/wire_format.py
src/notdot/__init__.py
src/notdot/bdbdatastore/__init__.py
src/notdot/bdbdatastore/rpc_pb2.py
src/notdot/bdbdatastore/socket_apiproxy_stub.py