Metadata-Version: 1.0
Name: bdbdatastore
Version: 0.2.2
Summary: An alternate datastore backend for App Engine, implemented using BDB JE.
Home-page: http://arachnid.github.com/bdbdatastore/
Author: Nick Johnson
Author-email: arachnid at notdot dot net
License: Apache License 2.0
Keywords: appengine,gae,bdb
Platform: UNKNOWN
Classifier: Development Status :: 5 - Production/Stable
Classifier: Environment :: Web Environment
Classifier: Intended Audience :: Developers
Classifier: License :: OSI Approved :: Apache Software License
Classifier: Natural Language :: English
Classifier: Operating System :: OS Independent
Classifier: Programming Language :: Java
Classifier: Programming Language :: Python
Classifier: Topic :: Internet :: WWW/HTTP
